wt/__init__.py
wt/base.py
wt/cli.py
wt/decorators.py
wt/engine.py
wt/exceptions.py
wt/html.py
wt/jinja.py
wt/md.py
wt/paginator.py
wt/server.py
wt/utils.py
wt/fixtures/bar.md
wt/fixtures/baz.md
wt/fixtures/foo.md
wt/fixtures/logo96.png
wt/fixtures/style.css
wt/fixtures/wt.yaml
wt/templates/404.html
wt/templates/atom.xml
wt/templates/base.html
wt/templates/content.html
wt/templates/mainpage.html
wt-2.1.1.dist-info/LICENSE.txt
wt-2.1.1.dist-info/METADATA
wt-2.1.1.dist-info/WHEEL
wt-2.1.1.dist-info/entry_points.txt
wt-2.1.1.dist-info/top_level.txt
wt-2.1.1.dist-info/RECORD
