Metadata-Version: 2.1
Name: wt
Version: 2.1.1
Summary: Static blog generator
Home-page: https://github.com/ysegorov/wt
Author: Yuri Egorov
Author-email: ysegorov@gmail.com
License: MIT
Keywords: blog static site generator
Platform: UNKNOWN
Classifier: Development Status :: 4 - Beta
Classifier: Intended Audience :: Developers
Classifier: Topic :: Software Development :: Build Tools
Classifier: License :: OSI Approved :: MIT License
Classifier: Programming Language :: Python :: 3
Classifier: Programming Language :: Python :: 3.5
Classifier: Programming Language :: Python :: 3.6
Classifier: Programming Language :: Python :: 3.7
Requires-Dist: markdown (>=3.0.1)
Requires-Dist: jinja2 (>=2.10)
Requires-Dist: pyyaml (>=3.13)
Requires-Dist: cached-property (>=1.3.0)
Provides-Extra: dev
Requires-Dist: twine (>=1.8.1) ; extra == 'dev'
Requires-Dist: coverage (>=4.2) ; extra == 'dev'
Requires-Dist: pytest (>=3.7.0) ; extra == 'dev'
Requires-Dist: pytest-cov (>=2.3.1) ; extra == 'dev'
Requires-Dist: pytest-describe (>=0.11.0) ; extra == 'dev'
